<?xml version="1.0" encoding="utf-8" ?>
<dwsync>
<file name="animate.css" server="C:/xampp/htdocs/testephp/" local="131353501700000000" remote="131353501700000000" Dst="2" />
<file name="bootstrap.css" server="C:/xampp/htdocs/testephp/" local="131139464080000000" remote="131139464080000000" Dst="2" />
<file name="bootstrap.min.css" server="C:/xampp/htdocs/testephp/" local="131139464080000000" remote="131139464080000000" Dst="2" />
<file name="ex10.css" server="C:/xampp/htdocs/testephp/" local="131518091828961242" remote="131518091820000000" Dst="2" />
<file name="ex11.css" server="C:/xampp/htdocs/testephp/" local="131520633042490536" remote="131520633040000000" Dst="2" />
<file name="ex12.css" server="C:/xampp/htdocs/testephp/" local="131520646941237510" remote="131520646940000000" Dst="2" />
<file name="ex14.css" server="C:/xampp/htdocs/testephp/" local="131530127768077377" remote="131530127760000000" Dst="2" />
<file name="ex15.css" server="C:/xampp/htdocs/testephp/" local="131530188415194502" remote="131530188410000000" Dst="2" />
<file name="ex16.css" server="C:/xampp/htdocs/testephp/" local="131532676203810119" remote="131532676200000000" Dst="2" />
<file name="ex7.css" server="C:/xampp/htdocs/testephp/" local="131512084267400000" remote="131512084260000000" Dst="2" />
<file name="ex8.css" server="C:/xampp/htdocs/testephp/" local="131512033579516532" remote="131512033570000000" Dst="2" />
<file name="reset.css" server="C:/xampp/htdocs/testephp/" local="130676437800000000" remote="130676437800000000" Dst="2" />
<file name="slide.css" server="C:/xampp/htdocs/testephp/" local="131536219419672184" remote="131536219410000000" Dst="2" />
</dwsync>